[
    {
        "event": "1203594102",
        "file_name": "1.glb",
        "id": "1",
        "m": "125.34",
        "run": "199319",
        "type": "H4l"
    },
    {
        "event": "1430970868",
        "file_name": "2.glb",
        "id": "2",
        "m": "122.0",
        "run": "202178",
        "type": "H4l"
    },
    {
        "event": "635670564",
        "file_name": "3.glb",
        "id": "3",
        "m": "121.81",
        "run": "201707",
        "type": "H4l"
    },
    {
        "event": "421267699",
        "file_name": "4.glb",
        "id": "4",
        "m": "125.16",
        "run": "202299",
        "type": "H4l"
    },
    {
        "event": "805047482",
        "file_name": "5.glb",
        "id": "5",
        "m": "125.37",
        "run": "201707",
        "type": "H4l"
    },
    {
        "event": "137440354",
        "file_name": "6.glb",
        "id": "6",
        "m": "126.48",
        "run": "195099",
        "type": "H4l"
    },
    {
        "event": "1357605031",
        "file_name": "7.glb",
        "id": "7",
        "m": "128.58",
        "run": "201191",
        "type": "H4l"
    },
    {
        "event": "27000461",
        "file_name": "8.glb",
        "id": "8",
        "m": "121.56",
        "run": "198213",
        "type": "H4l"
    },
    {
        "event": "153791279",
        "file_name": "9.glb",
        "id": "9",
        "m": "126.29",
        "run": "200466",
        "type": "H4l"
    },
    {
        "event": "216745941",
        "file_name": "10.glb",
        "id": "10",
        "m": "124.63",
        "run": "201174",
        "type": "H4l"
    },
    {
        "event": "1605749984",
        "file_name": "11.glb",
        "id": "11",
        "m": "129.91",
        "run": "200091",
        "type": "H4l"
    },
    {
        "event": "1044502715",
        "file_name": "12.glb",
        "id": "12",
        "m": "113.66",
        "run": "195397",
        "type": "Zmumu"
    },
    {
        "event": "1044442517",
        "file_name": "13.glb",
        "id": "13",
        "m": "89.28",
        "run": "195397",
        "type": "Zmumu"
    },
    {
        "event": "1044626847",
        "file_name": "14.glb",
        "id": "14",
        "m": "90.34",
        "run": "195397",
        "type": "Zmumu"
    },
    {
        "event": "1044596239",
        "file_name": "15.glb",
        "id": "15",
        "m": "89.05",
        "run": "195397",
        "type": "Zmumu"
    },
    {
        "event": "1044611279",
        "file_name": "16.glb",
        "id": "16",
        "m": "82.32",
        "run": "195397",
        "type": "Zmumu"
    },
    {
        "event": "1045087271",
        "file_name": "17.glb",
        "id": "17",
        "m": "95.34",
        "run": "195397",
        "type": "Zmumu"
    },
    {
        "event": "1044618374",
        "file_name": "18.glb",
        "id": "18",
        "m": "79.76",
        "run": "195397",
        "type": "Zmumu"
    },
    {
        "event": "1044511288",
        "file_name": "19.glb",
        "id": "19",
        "m": "91.34",
        "run": "195397",
        "type": "Zmumu"
    },
    {
        "event": "1044625528",
        "file_name": "20.glb",
        "id": "20",
        "m": "97.86",
        "run": "195397",
        "type": "Zmumu"
    },
    {
        "event": "1044611124",
        "file_name": "21.glb",
        "id": "21",
        "m": "87.59",
        "run": "195397",
        "type": "Zmumu"
    },
    {
        "event": "1044513202",
        "file_name": "22.glb",
        "id": "22",
        "m": "90.51",
        "run": "195397",
        "type": "Zmumu"
    },
    {
        "event": "1044437987",
        "file_name": "23.glb",
        "id": "23",
        "m": "103.55",
        "run": "195397",
        "type": "Zmumu"
    },
    {
        "event": "1044491827",
        "file_name": "24.glb",
        "id": "24",
        "m": "92.96",
        "run": "195397",
        "type": "Zmumu"
    },
    {
        "event": "1044468595",
        "file_name": "25.glb",
        "id": "25",
        "m": "65.25",
        "run": "195397",
        "type": "Zmumu"
    },
    {
        "event": "1045084627",
        "file_name": "26.glb",
        "id": "26",
        "m": "89.37",
        "run": "195397",
        "type": "Zmumu"
    },
    {
        "event": "1045126627",
        "file_name": "27.glb",
        "id": "27",
        "m": "68.61",
        "run": "195397",
        "type": "Zmumu"
    },
    {
        "event": "1045243075",
        "file_name": "28.glb",
        "id": "28",
        "m": "64.1",
        "run": "195397",
        "type": "Zmumu"
    },
    {
        "event": "1044477423",
        "file_name": "29.glb",
        "id": "29",
        "m": "68.52",
        "run": "195397",
        "type": "Zmumu"
    },
    {
        "event": "1044667679",
        "file_name": "30.glb",
        "id": "30",
        "m": "86.91",
        "run": "195397",
        "type": "Zmumu"
    },
    {
        "event": "1044864255",
        "file_name": "31.glb",
        "id": "31",
        "m": "85.63",
        "run": "195397",
        "type": "Zmumu"
    },
    {
        "event": "1045216809",
        "file_name": "32.glb",
        "id": "32",
        "m": "88.24",
        "run": "195397",
        "type": "Zmumu"
    },
    {
        "event": "1045209881",
        "file_name": "33.glb",
        "id": "33",
        "m": "90.49",
        "run": "195397",
        "type": "Zmumu"
    },
    {
        "event": "1044519066",
        "file_name": "34.glb",
        "id": "34",
        "m": "90.94",
        "run": "195397",
        "type": "Zmumu"
    },
    {
        "event": "1044470685",
        "file_name": "35.glb",
        "id": "35",
        "m": "92.21",
        "run": "195397",
        "type": "Zmumu"
    },
    {
        "event": "1044917917",
        "file_name": "36.glb",
        "id": "36",
        "m": "85.16",
        "run": "195397",
        "type": "Zmumu"
    },
    {
        "event": "1044923118",
        "file_name": "37.glb",
        "id": "37",
        "m": "75.47",
        "run": "195397",
        "type": "Zmumu"
    },
    {
        "event": "1044394752",
        "file_name": "38.glb",
        "id": "38",
        "m": "86.59",
        "run": "195397",
        "type": "Zmumu"
    },
    {
        "event": "1044443200",
        "file_name": "39.glb",
        "id": "39",
        "m": "100.19",
        "run": "195397",
        "type": "Zmumu"
    },
    {
        "event": "1044482336",
        "file_name": "40.glb",
        "id": "40",
        "m": "113.52",
        "run": "195397",
        "type": "Zmumu"
    },
    {
        "event": "1044604416",
        "file_name": "41.glb",
        "id": "41",
        "m": "90.93",
        "run": "195397",
        "type": "Zmumu"
    },
    {
        "event": "1045097760",
        "file_name": "42.glb",
        "id": "42",
        "m": "90.34",
        "run": "195397",
        "type": "Zmumu"
    },
    {
        "event": "1045219504",
        "file_name": "43.glb",
        "id": "43",
        "m": "85.81",
        "run": "195397",
        "type": "Zmumu"
    },
    {
        "event": "1045226192",
        "file_name": "44.glb",
        "id": "44",
        "m": "65.78",
        "run": "195397",
        "type": "Zmumu"
    },
    {
        "event": "1045269740",
        "file_name": "45.glb",
        "id": "45",
        "m": "104.06",
        "run": "195397",
        "type": "Zmumu"
    },
    {
        "event": "1045629467",
        "file_name": "46.glb",
        "id": "46",
        "m": "78.95",
        "run": "195397",
        "type": "Zmumu"
    },
    {
        "event": "1046139531",
        "file_name": "47.glb",
        "id": "47",
        "m": "93.32",
        "run": "195397",
        "type": "Zmumu"
    },
    {
        "event": "1046343561",
        "file_name": "48.glb",
        "id": "48",
        "m": "77.23",
        "run": "195397",
        "type": "Zmumu"
    },
    {
        "event": "1045401372",
        "file_name": "49.glb",
        "id": "49",
        "m": "111.76",
        "run": "195397",
        "type": "Zmumu"
    },
    {
        "event": "1045371884",
        "file_name": "50.glb",
        "id": "50",
        "m": "92.62",
        "run": "195397",
        "type": "Zmumu"
    },
    {
        "event": "1045818060",
        "file_name": "51.glb",
        "id": "51",
        "m": "88.1",
        "run": "195397",
        "type": "Zmumu"
    },
    {
        "event": "1045554657",
        "file_name": "52.glb",
        "id": "52",
        "m": "93.54",
        "run": "195397",
        "type": "Zmumu"
    },
    {
        "event": "1045605601",
        "file_name": "53.glb",
        "id": "53",
        "m": "99.56",
        "run": "195397",
        "type": "Zmumu"
    },
    {
        "event": "1045650513",
        "file_name": "54.glb",
        "id": "54",
        "m": "86.37",
        "run": "195397",
        "type": "Zmumu"
    },
    {
        "event": "1045780417",
        "file_name": "55.glb",
        "id": "55",
        "m": "90.97",
        "run": "195397",
        "type": "Zmumu"
    },
    {
        "event": "1045495760",
        "file_name": "56.glb",
        "id": "56",
        "m": "93.97",
        "run": "195397",
        "type": "Zmumu"
    },
    {
        "event": "1045596064",
        "file_name": "57.glb",
        "id": "57",
        "m": "94.29",
        "run": "195397",
        "type": "Zmumu"
    },
    {
        "event": "1045718128",
        "file_name": "58.glb",
        "id": "58",
        "m": "94.64",
        "run": "195397",
        "type": "Zmumu"
    },
    {
        "event": "1045899296",
        "file_name": "59.glb",
        "id": "59",
        "m": "88.97",
        "run": "195397",
        "type": "Zmumu"
    },
    {
        "event": "1046039792",
        "file_name": "60.glb",
        "id": "60",
        "m": "89.93",
        "run": "195397",
        "type": "Zmumu"
    },
    {
        "event": "1046078825",
        "file_name": "61.glb",
        "id": "61",
        "m": "91.54",
        "run": "195397",
        "type": "Zmumu"
    },
    {
        "event": "375757843",
        "file_name": "62.glb",
        "id": "62",
        "m": "90.64",
        "run": "195113",
        "type": "Zee"
    },
    {
        "event": "376506499",
        "file_name": "63.glb",
        "id": "63",
        "m": "63.87",
        "run": "195113",
        "type": "Zee"
    },
    {
        "event": "376364145",
        "file_name": "64.glb",
        "id": "64",
        "m": "90.06",
        "run": "195113",
        "type": "Zee"
    },
    {
        "event": "376076502",
        "file_name": "65.glb",
        "id": "65",
        "m": "87.55",
        "run": "195113",
        "type": "Zee"
    },
    {
        "event": "376261830",
        "file_name": "66.glb",
        "id": "66",
        "m": "95.73",
        "run": "195113",
        "type": "Zee"
    },
    {
        "event": "376506742",
        "file_name": "67.glb",
        "id": "67",
        "m": "90.91",
        "run": "195113",
        "type": "Zee"
    },
    {
        "event": "376218377",
        "file_name": "68.glb",
        "id": "68",
        "m": "88.99",
        "run": "195113",
        "type": "Zee"
    },
    {
        "event": "376372905",
        "file_name": "69.glb",
        "id": "69",
        "m": "96.34",
        "run": "195113",
        "type": "Zee"
    },
    {
        "event": "376194224",
        "file_name": "70.glb",
        "id": "70",
        "m": "70.08",
        "run": "195113",
        "type": "Zee"
    },
    {
        "event": "375521525",
        "file_name": "71.glb",
        "id": "71",
        "m": "83.32",
        "run": "195113",
        "type": "Zee"
    },
    {
        "event": "376381317",
        "file_name": "72.glb",
        "id": "72",
        "m": "92.79",
        "run": "195113",
        "type": "Zee"
    },
    {
        "event": "376471269",
        "file_name": "73.glb",
        "id": "73",
        "m": "119.84",
        "run": "195113",
        "type": "Zee"
    },
    {
        "event": "375899295",
        "file_name": "74.glb",
        "id": "74",
        "m": "76.95",
        "run": "195113",
        "type": "Zee"
    },
    {
        "event": "375943485",
        "file_name": "75.glb",
        "id": "75",
        "m": "91.57",
        "run": "195113",
        "type": "Zee"
    },
    {
        "event": "376213389",
        "file_name": "76.glb",
        "id": "76",
        "m": "90.43",
        "run": "195113",
        "type": "Zee"
    },
    {
        "event": "376323429",
        "file_name": "77.glb",
        "id": "77",
        "m": "71.52",
        "run": "195113",
        "type": "Zee"
    },
    {
        "event": "375749246",
        "file_name": "78.glb",
        "id": "78",
        "m": "88.88",
        "run": "195113",
        "type": "Zee"
    },
    {
        "event": "376250766",
        "file_name": "79.glb",
        "id": "79",
        "m": "92.02",
        "run": "195113",
        "type": "Zee"
    },
    {
        "event": "376256638",
        "file_name": "80.glb",
        "id": "80",
        "m": "91.17",
        "run": "195113",
        "type": "Zee"
    },
    {
        "event": "375598547",
        "file_name": "81.glb",
        "id": "81",
        "m": "98.54",
        "run": "195113",
        "type": "Zee"
    },
    {
        "event": "376077019",
        "file_name": "82.glb",
        "id": "82",
        "m": "98.13",
        "run": "195113",
        "type": "Zee"
    },
    {
        "event": "375963932",
        "file_name": "83.glb",
        "id": "83",
        "m": "91.65",
        "run": "195113",
        "type": "Zee"
    },
    {
        "event": "375955820",
        "file_name": "84.glb",
        "id": "84",
        "m": "91.32",
        "run": "195113",
        "type": "Zee"
    },
    {
        "event": "376234716",
        "file_name": "85.glb",
        "id": "85",
        "m": "88.66",
        "run": "195113",
        "type": "Zee"
    },
    {
        "event": "375597768",
        "file_name": "86.glb",
        "id": "86",
        "m": "87.61",
        "run": "195113",
        "type": "Zee"
    },
    {
        "event": "375830168",
        "file_name": "87.glb",
        "id": "87",
        "m": "87.79",
        "run": "195113",
        "type": "Zee"
    },
    {
        "event": "375862215",
        "file_name": "88.glb",
        "id": "88",
        "m": "86.08",
        "run": "195113",
        "type": "Zee"
    },
    {
        "event": "375542210",
        "file_name": "89.glb",
        "id": "89",
        "m": "105.7",
        "run": "195113",
        "type": "Zee"
    },
    {
        "event": "375974098",
        "file_name": "90.glb",
        "id": "90",
        "m": "92.22",
        "run": "195113",
        "type": "Zee"
    },
    {
        "event": "376113362",
        "file_name": "91.glb",
        "id": "91",
        "m": "96.39",
        "run": "195113",
        "type": "Zee"
    },
    {
        "event": "376005650",
        "file_name": "92.glb",
        "id": "92",
        "m": "89.82",
        "run": "195113",
        "type": "Zee"
    },
    {
        "event": "376455202",
        "file_name": "93.glb",
        "id": "93",
        "m": "106.22",
        "run": "195113",
        "type": "Zee"
    },
    {
        "event": "376538930",
        "file_name": "94.glb",
        "id": "94",
        "m": "82.61",
        "run": "195113",
        "type": "Zee"
    },
    {
        "event": "375733844",
        "file_name": "95.glb",
        "id": "95",
        "m": "90.64",
        "run": "195113",
        "type": "Zee"
    },
    {
        "event": "376350548",
        "file_name": "96.glb",
        "id": "96",
        "m": "85.47",
        "run": "195113",
        "type": "Zee"
    },
    {
        "event": "378155046",
        "file_name": "97.glb",
        "id": "97",
        "m": "98.51",
        "run": "195113",
        "type": "Zee"
    },
    {
        "event": "378524950",
        "file_name": "98.glb",
        "id": "98",
        "m": "76.83",
        "run": "195113",
        "type": "Zee"
    },
    {
        "event": "378777142",
        "file_name": "99.glb",
        "id": "99",
        "m": "90.5",
        "run": "195113",
        "type": "Zee"
    },
    {
        "event": "378731326",
        "file_name": "100.glb",
        "id": "100",
        "m": "95.17",
        "run": "195113",
        "type": "Zee"
    },
    {
        "event": "378267533",
        "file_name": "101.glb",
        "id": "101",
        "m": "94.89",
        "run": "195113",
        "type": "Zee"
    },
    {
        "event": "378534261",
        "file_name": "102.glb",
        "id": "102",
        "m": "94.23",
        "run": "195113",
        "type": "Zee"
    },
    {
        "event": "378695909",
        "file_name": "103.glb",
        "id": "103",
        "m": "91.37",
        "run": "195113",
        "type": "Zee"
    },
    {
        "event": "377904555",
        "file_name": "104.glb",
        "id": "104",
        "m": "97.42",
        "run": "195113",
        "type": "Zee"
    },
    {
        "event": "378139427",
        "file_name": "105.glb",
        "id": "105",
        "m": "96.08",
        "run": "195113",
        "type": "Zee"
    },
    {
        "event": "378210179",
        "file_name": "106.glb",
        "id": "106",
        "m": "90.83",
        "run": "195113",
        "type": "Zee"
    },
    {
        "event": "378842903",
        "file_name": "107.glb",
        "id": "107",
        "m": "67.97",
        "run": "195113",
        "type": "Zee"
    },
    {
        "event": "377954228",
        "file_name": "108.glb",
        "id": "108",
        "m": "91.31",
        "run": "195113",
        "type": "Zee"
    },
    {
        "event": "378119476",
        "file_name": "109.glb",
        "id": "109",
        "m": "99.37",
        "run": "195113",
        "type": "Zee"
    },
    {
        "event": "377739994",
        "file_name": "110.glb",
        "id": "110",
        "m": "93.78",
        "run": "195113",
        "type": "Zee"
    },
    {
        "event": "377823418",
        "file_name": "111.glb",
        "id": "111",
        "m": "90.75",
        "run": "195113",
        "type": "Zee"
    }
]